openapi_dto/__init__.py
openapi_dto/__main__.py
openapi_dto/cli.py
openapi_dto/config.py
openapi_dto/engine/__init__.py
openapi_dto/engine/base.py
openapi_dto/engine/dataclasses.py
openapi_dto/models.py
openapi_dto/registry.py
openapi_dto-0.1.8.dist-info/LICENSE
openapi_dto-0.1.8.dist-info/METADATA
openapi_dto-0.1.8.dist-info/WHEEL
openapi_dto-0.1.8.dist-info/entry_points.txt
openapi_dto-0.1.8.dist-info/RECORD
