Metadata-Version: 2.1
Name: openapi-dto
Version: 0.1.8
Summary: A CLI tool for automated DTO generation using OpenAPI schema
License: Apache 2.0
Author: Kacper Łukawski
Author-email: kacper.lukawsk@embassy.ai
Requires-Python: >=3.9,<4.0
Classifier: License :: Other/Proprietary License
Classifier: Programming Language :: Python :: 3
Classifier: Programming Language :: Python :: 3.9
Classifier: Programming Language :: Python :: 3.10
Classifier: Programming Language :: Python :: 3.11
Requires-Dist: camel-converter (>=3.0.0,<4.0.0)
Requires-Dist: dataclasses-json (>=0.5.7,<0.6.0)
Requires-Dist: typer (>=0.7.0,<0.8.0)
